idex/__init__.py
idex/client.py
idex/enums.py
idex/exceptions.py
idex/signing.py
idex/utils.py
idex/contracts/__init__.py
python_idex-3.0.0.dist-info/LICENSE
python_idex-3.0.0.dist-info/METADATA
python_idex-3.0.0.dist-info/WHEEL
python_idex-3.0.0.dist-info/top_level.txt
python_idex-3.0.0.dist-info/RECORD
