Metadata-Version: 2.1
Name: python-idex
Version: 3.0.0
Summary: IDEX v3 REST API python implementation
Home-page: https://github.com/sammchardy/python-idex
Author: Sam McHardy
Author-email: 
License: MIT
Keywords: idex exchange rest api ethereum eth eos
Platform: UNKNOWN
Classifier: Intended Audience :: Developers
Classifier: License :: OSI Approved :: MIT License
Classifier: Operating System :: OS Independent
Classifier: Programming Language :: Python :: 3
Classifier: Programming Language :: Python :: 3.6
Classifier: Programming Language :: Python :: 3.7
Classifier: Programming Language :: Python :: 3.8
Classifier: Programming Language :: Python :: 3.9
Classifier: Programming Language :: Python :: 3.10
Classifier: Programming Language :: Python
Classifier: Topic :: Software Development :: Libraries :: Python Modules
License-File: LICENSE
Requires-Dist: aiohttp
Requires-Dist: requests
Requires-Dist: web3
